setup.py
qamanage/__init__.py
qamanage/ocr_api.py
qamanage/oracle_api.py
qamanage/public_api.py
qamanage.egg-info/PKG-INFO
qamanage.egg-info/SOURCES.txt
qamanage.egg-info/dependency_links.txt
qamanage.egg-info/requires.txt
qamanage.egg-info/top_level.txt