Metadata-Version: 1.0
Name: qamanage
Version: 0.0.14
Summary: A public script library
Home-page: https://github.com/lin54241930/qamanage.git
Author: Linxu
Author-email: lin54241930@163.com
License: Apache License 2.0
Keywords: qamanage
Platform: any
